afqinsight/__init__.py
afqinsight/_serial_bagging.py
afqinsight/_version.py
afqinsight/cross_validate.py
afqinsight/datasets.py
afqinsight/h5io.py
afqinsight/match.py
afqinsight/parametric.py
afqinsight/pipeline.py
afqinsight/plot.py
afqinsight/transform.py
afqinsight/utils.py
afqinsight/augmentation/__init__.py
afqinsight/augmentation/augmentation.py
afqinsight/augmentation/dtw.py
afqinsight/data/classification_data/nodes.csv
afqinsight/data/classification_data/subjects.csv
afqinsight/data/regression_data/nodes.csv
afqinsight/data/regression_data/subjects.csv
afqinsight/data/test_data/nodes.csv
afqinsight/data/test_data/subjects.csv
afqinsight/data/test_data/test_data_y.npy
afqinsight/data/test_data/test_multicol2dicts_label_dicts.json
afqinsight/data/test_data/test_multicol2sets_label_sets.npy
afqinsight/data/test_data/test_remove_group_x.npy
afqinsight/data/test_data/test_remove_groups_x.npy
afqinsight/data/test_data/test_select_group_x.npy
afqinsight/data/test_data/test_select_groups_x.npy
afqinsight/data/test_data/test_shuffle_group_x.npy
afqinsight/data/test_data/test_transform_cols.npy
afqinsight/data/test_data/test_transform_groups.npy
afqinsight/data/test_data/test_transform_x.npy
afqinsight/neurocombat_sklearn/__init__.py
afqinsight/neurocombat_sklearn/neurocombat_sklearn.py
afqinsight/neurocombat_sklearn/tests/test_neurocombat.py
afqinsight/nn/__init__.py
afqinsight/nn/pt_models.py
afqinsight/nn/tf_models.py
afqinsight/nn/utils.py
afqinsight/nn/tests/test_compare_py_tf.py
afqinsight/nn/tests/test_pt_models.py
afqinsight/nn/tests/test_tf_models.py
afqinsight/tests/test_augmentation.py
afqinsight/tests/test_bagging.py
afqinsight/tests/test_cross_validate.py
afqinsight/tests/test_datasets.py
afqinsight/tests/test_h5io.py
afqinsight/tests/test_match.py
afqinsight/tests/test_pipelines.py
afqinsight/tests/test_transform.py
afqinsight-0.7.1.dist-info/LICENSE
afqinsight-0.7.1.dist-info/METADATA
afqinsight-0.7.1.dist-info/WHEEL
afqinsight-0.7.1.dist-info/top_level.txt
afqinsight-0.7.1.dist-info/RECORD
