Metadata-Version: 2.2
Name: afqinsight
Version: 0.7.1
Summary: AFQ-Insight: Statistical Learning for Tractometry
Home-page: https://tractometry.org/AFQ-Insight
Download-URL: https://github.com/tractometry/AFQ-Insight
Author: Adam Richie-Halford
Author-email: richiehalford@gmail.com
Maintainer: Ariel Rokem
Maintainer-email: arokem@gmail.com
License: BSD License
Platform: OS Independent
Classifier: Development Status :: 3 - Alpha
Classifier: Environment :: Console
Classifier: Intended Audience :: Science/Research
Classifier: License :: OSI Approved :: BSD License
Classifier: Operating System :: OS Independent
Classifier: Programming Language :: Python
Classifier: Topic :: Scientific/Engineering
Requires-Python: >=3.11
License-File: LICENSE
Requires-Dist: numpy==2.0.0
Requires-Dist: scipy==1.13.1
Requires-Dist: dipy>=1.9.0
Requires-Dist: matplotlib>=3.9
Requires-Dist: groupyr>=0.3.4
Requires-Dist: pandas==2.2.3
Requires-Dist: requests
Requires-Dist: seaborn==0.13.0
Requires-Dist: scikit-learn==1.5.2
Requires-Dist: sklearn_pandas>=2.0.0
Requires-Dist: tqdm
Requires-Dist: statsmodels>=0.14.4
Provides-Extra: tables
Requires-Dist: tables==3.10.2; extra == "tables"
Provides-Extra: torch
Requires-Dist: torch; extra == "torch"
Requires-Dist: torchvision; extra == "torch"
Provides-Extra: tf
Requires-Dist: tensorflow>=2.18.0; extra == "tf"
Provides-Extra: dev
Requires-Dist: matplotlib; extra == "dev"
Requires-Dist: numpydoc; extra == "dev"
Requires-Dist: pre-commit; extra == "dev"
Requires-Dist: pydocstyle; extra == "dev"
Requires-Dist: pytest-cov; extra == "dev"
Requires-Dist: pytest-xdist[psutil]; extra == "dev"
Requires-Dist: pytest; extra == "dev"
Requires-Dist: s3fs; extra == "dev"
Requires-Dist: sphinx; extra == "dev"
Requires-Dist: sphinx-gallery; extra == "dev"
Requires-Dist: sphinx-panels; extra == "dev"
Requires-Dist: pydata-sphinx-theme==0.15.4; extra == "dev"
Provides-Extra: maint
Requires-Dist: rapidfuzz; extra == "maint"
Provides-Extra: all
Requires-Dist: tables==3.10.2; extra == "all"
Requires-Dist: torch; extra == "all"
Requires-Dist: torchvision; extra == "all"
Requires-Dist: tensorflow>=2.18.0; extra == "all"
Requires-Dist: matplotlib; extra == "all"
Requires-Dist: numpydoc; extra == "all"
Requires-Dist: pre-commit; extra == "all"
Requires-Dist: pydocstyle; extra == "all"
Requires-Dist: pytest-cov; extra == "all"
Requires-Dist: pytest-xdist[psutil]; extra == "all"
Requires-Dist: pytest; extra == "all"
Requires-Dist: s3fs; extra == "all"
Requires-Dist: sphinx; extra == "all"
Requires-Dist: sphinx-gallery; extra == "all"
Requires-Dist: sphinx-panels; extra == "all"
Requires-Dist: pydata-sphinx-theme==0.15.4; extra == "all"
Requires-Dist: rapidfuzz; extra == "all"
Dynamic: download-url
